[
    {
        "specname": "Клиническая лабораторная диагностика",
        "tags": null,
        "programs": {
            "id": 2781,
            "katalog": "Здравоохранение/zdravoohranenie",
            "type_zdrav": "ВО",
            "spec": "Профессиональная переподготовка",
            "name": "Лабораторная генетика",
            "price": 49800,
            "hour": 600,
            "nmoSpec": null,
            "linkNmo": null,
            "url": "https://company.ru/katalog/zdravoohranenie/kurs-laboratornaya-genetika/",
            "final_url": "https://company.ru/katalog/zdravoohranenie/kurs-laboratornaya-genetika/?program=Лабораторная генетика&header=Курс ПП Лабораторная генетика&cost=49800&tovar=2781&sendsay_email=${ Recipient.Email }"
        }
    },
    {
        "specname": "Клиническая лабораторная диагностика",
        "tags": null,
        "programs": {
            "id": 2743,
            "katalog": "Здравоохранение/zdravoohranenie",
            "type_zdrav": "ВО",
            "spec": "Профессиональная переподготовка",
            "name": "Бактериология",
            "price": 49800,
            "hour": 600,
            "nmoSpec": null,
            "linkNmo": null,
            "url": "https://company.ru/katalog/zdravoohranenie/kurs-bakteriologiya/",
            "final_url": "https://company.ru/katalog/zdravoohranenie/kurs-bakteriologiya/?program=Бактериология&header=Курс ПП Бактериология&cost=49800&tovar=2743&sendsay_email=${ Recipient.Email }"
        }
    },
    {
        "specname": "Клиническая лабораторная диагностика",
        "tags": {
            "tag": "#HIT#"
        },
        "programs": {
            "id": 1531,
            "katalog": "Здравоохранение/zdravoohranenie",
            "type_zdrav": "ВО",
            "spec": "Профессиональная переподготовка",
            "name": "Организация здравоохранения и общественное здоровье",
            "price": 49800,
            "hour": 600,
            "nmoSpec": null,
            "linkNmo": null,
            "url": "https://company.ru/katalog/zdravoohranenie/kurs-organizatsiya-zdravoohraneniya-i-obschestvennoe-zdorove/",
            "final_url": "https://company.ru/katalog/zdravoohranenie/kurs-organizatsiya-zdravoohraneniya-i-obschestvennoe-zdorove/?program=Организация здравоохранения и общественное здоровье&header=Курс ПП Организация здравоохранения и общественное здоровье&cost=49800&tovar=1531&sendsay_email=${ Recipient.Email }"
        }
    },
    {
        "specname": "Клиническая лабораторная диагностика",
        "tags": null,
        "programs": {
            "id": 2745,
            "katalog": "Здравоохранение/zdravoohranenie",
            "type_zdrav": "ВО",
            "spec": "Профессиональная переподготовка",
            "name": "Вирусология",
            "price": 49800,
            "hour": 600,
            "nmoSpec": null,
            "linkNmo": null,
            "url": "https://company.ru/katalog/zdravoohranenie/kurs-virusologiya/",
            "final_url": "https://company.ru/katalog/zdravoohranenie/kurs-virusologiya/?program=Вирусология&header=Курс ПП Вирусология&cost=49800&tovar=2745&sendsay_email=${ Recipient.Email }"
        }
    },
    {
        "specname": "Клиническая лабораторная диагностика",
        "tags": null,
        "programs": {
            "id": 16177,
            "katalog": "Здравоохранение/zdravoohranenie",
            "type_zdrav": "ВО",
            "spec": "Профессиональная переподготовка",
            "name": "Медицинская микробиология",
            "price": 49800,
            "hour": 600,
            "nmoSpec": null,
            "linkNmo": null,
            "url": "https://company.ru/katalog/zdravoohranenie/kurs-meditsinskaya-mikrobiologiya-2/",
            "final_url": "https://company.ru/katalog/zdravoohranenie/kurs-meditsinskaya-mikrobiologiya-2/?program=Медицинская микробиология&header=Курс ПП Медицинская микробиология&cost=49800&tovar=16177&sendsay_email=${ Recipient.Email }"
        }
    },
    {
        "specname": "Клиническая лабораторная диагностика",
        "tags": {
            "tag": "#NEW#"
        },
        "programs": {
            "id": 16067,
            "katalog": "Здравоохранение/zdravoohranenie",
            "type_zdrav": "ВО",
            "spec": "Профессиональная переподготовка",
            "name": "Клиническая лабораторная диагностика",
            "price": 49800,
            "hour": 600,
            "nmoSpec": null,
            "linkNmo": null,
            "url": "https://company.ru/katalog/zdravoohranenie/kurs-klinicheskaya-laboratornaya-diagnostika-2/",
            "final_url": "https://company.ru/katalog/zdravoohranenie/kurs-klinicheskaya-laboratornaya-diagnostika-2/?program=Клиническая лабораторная диагностика&header=Курс ПП Клиническая лабораторная диагностика&cost=49800&tovar=16067&sendsay_email=${ Recipient.Email }"
        }
    }
]