[
    {
        "specname": "Стоматология ортопедическая",
        "programs": [
            {
                "nmo_spec": "Стоматология ортопедическая",
                "nmo_prog": "Стоматология ортопедическая",
                "price": "2448",
                "hour": "36",
                "date": "06.04.2022",
                "linkNmo": "https://clck.ru/337SSn"
            },
            {
                "nmo_spec": "Стоматология ортопедическая",
                "nmo_prog": "Стоматология ортопедическая: актуальные вопросы и инновационные решения",
                "price": "5032",
                "hour": "74",
                "date": "04.04.22",
                "linkNmo": "https://clck.ru/337STY"
            },
            {
                "nmo_spec": "Стоматология ортопедическая",
                "nmo_prog": "Современные аспекты ортопедической помощи населению",
                "price": "9792",
                "hour": "144",
                "date": "18.02.22",
                "linkNmo": "https://clck.ru/337SV6"
            },
            {
                "nmo_spec": "Стоматология ортопедическая",
                "nmo_prog": "Стоматология ортопедическая",
                "price": "9792",
                "hour": "144",
                "date": "05.04.2022",
                "linkNmo": "https://clck.ru/337STp"
            },
            {
                "nmo_spec": "Стоматология ортопедическая",
                "nmo_prog": "Стоматология ортопедическая",
                "price": "19584",
                "hour": "288",
                "date": "06.04.2022",
                "linkNmo": "https://clck.ru/337SUC"
            }
        ]
    }
]